np_queuey-0.2.47.dist-info/METADATA
np_queuey-0.2.47.dist-info/WHEEL
np_queuey-0.2.47.dist-info/entry_points.txt
np_queuey/__init__.py
np_queuey/hueys/.mypy_cache/.gitignore
np_queuey/hueys/.mypy_cache/3.11/@plugins_snapshot.json
np_queuey/hueys/.mypy_cache/3.11/__future__.data.json
np_queuey/hueys/.mypy_cache/3.11/__future__.meta.json
np_queuey/hueys/.mypy_cache/3.11/_ast.data.json
np_queuey/hueys/.mypy_cache/3.11/_ast.meta.json
np_queuey/hueys/.mypy_cache/3.11/_asyncio.data.json
np_queuey/hueys/.mypy_cache/3.11/_asyncio.meta.json
np_queuey/hueys/.mypy_cache/3.11/_bz2.data.json
np_queuey/hueys/.mypy_cache/3.11/_bz2.meta.json
np_queuey/hueys/.mypy_cache/3.11/_codecs.data.json
np_queuey/hueys/.mypy_cache/3.11/_codecs.meta.json
np_queuey/hueys/.mypy_cache/3.11/_collections_abc.data.json
np_queuey/hueys/.mypy_cache/3.11/_collections_abc.meta.json
np_queuey/hueys/.mypy_cache/3.11/_compression.data.json
np_queuey/hueys/.mypy_cache/3.11/_compression.meta.json
np_queuey/hueys/.mypy_cache/3.11/_contextvars.data.json
np_queuey/hueys/.mypy_cache/3.11/_contextvars.meta.json
np_queuey/hueys/.mypy_cache/3.11/_ctypes.data.json
np_queuey/hueys/.mypy_cache/3.11/_ctypes.meta.json
np_queuey/hueys/.mypy_cache/3.11/_decimal.data.json
np_queuey/hueys/.mypy_cache/3.11/_decimal.meta.json
np_queuey/hueys/.mypy_cache/3.11/_frozen_importlib.data.json
np_queuey/hueys/.mypy_cache/3.11/_frozen_importlib.meta.json
np_queuey/hueys/.mypy_cache/3.11/_frozen_importlib_external.data.json
np_queuey/hueys/.mypy_cache/3.11/_frozen_importlib_external.meta.json
np_queuey/hueys/.mypy_cache/3.11/_io.data.json
np_queuey/hueys/.mypy_cache/3.11/_io.meta.json
np_queuey/hueys/.mypy_cache/3.11/_pickle.data.json
np_queuey/hueys/.mypy_cache/3.11/_pickle.meta.json
np_queuey/hueys/.mypy_cache/3.11/_queue.data.json
np_queuey/hueys/.mypy_cache/3.11/_queue.meta.json
np_queuey/hueys/.mypy_cache/3.11/_random.data.json
np_queuey/hueys/.mypy_cache/3.11/_random.meta.json
np_queuey/hueys/.mypy_cache/3.11/_sitebuiltins.data.json
np_queuey/hueys/.mypy_cache/3.11/_sitebuiltins.meta.json
np_queuey/hueys/.mypy_cache/3.11/_socket.data.json
np_queuey-0.2.47.dist-info/RECORD
