Metadata-Version: 2.1
Name: np_queuey
Version: 0.2.47
Summary: Tools for submitting and processing jobs through a message queue for Mindscope Neuropixels workflows.
Author-Email: Ben Hardcastle <ben.hardcastle@alleninstitute.org>
License: MIT
Classifier: Programming Language :: Python :: 3
Classifier: Programming Language :: Python :: 3.8
Classifier: Programming Language :: Python :: 3.9
Classifier: Programming Language :: Python :: 3.10
Classifier: Programming Language :: Python :: 3.11
Classifier: License :: OSI Approved :: MIT License
Classifier: Operating System :: Microsoft :: Windows
Classifier: Operating System :: POSIX :: Linux
Project-URL: Repository, https://github.com/AllenInstitute/np_queuey
Project-URL: Bug Tracker, https://github.com/AllenInstitute/np_queuey/issues
Requires-Python: >=3.9
Requires-Dist: huey>=2.4.5
Requires-Dist: np-config>=0.4.17
Requires-Dist: np-logging>=0.5.1
Requires-Dist: np-tools>=0.1.14
Requires-Dist: np-session>=0.6.38
Requires-Dist: typing-extensions>=4.5.0
Requires-Dist: np-jobs>=0.0.8
Requires-Dist: np-envs>=0.1.3
Requires-Dist: s3fs>=2023.10.0
Requires-Dist: universal-pathlib>=0.1.4
Requires-Dist: boto3>=1.1.0
Requires-Dist: npc_ephys
